pycounts_cxy24/__init__.py
pycounts_cxy24/plotting.py
pycounts_cxy24/pycounts_cxy24.py
pycounts_cxy24-0.1.0.dist-info/LICENSE
pycounts_cxy24-0.1.0.dist-info/METADATA
pycounts_cxy24-0.1.0.dist-info/WHEEL
pycounts_cxy24-0.1.0.dist-info/RECORD
